HaystackAgentBasicMemory/Agentchat.py
HaystackAgentBasicMemory/MemoryRecallNode.py
HaystackAgentBasicMemory/SaveToMemory.py
HaystackAgentBasicMemory/__init__.py
haystackagentbasicmemory-0.1.4.dist-info/METADATA
haystackagentbasicmemory-0.1.4.dist-info/WHEEL
haystackagentbasicmemory-0.1.4.dist-info/licenses/LICENSE
haystackagentbasicmemory-0.1.4.dist-info/RECORD
