Metadata-Version: 2.1
Name: haystackagentbasicmemory
Version: 0.1.4
Summary: Basic Memory library for Haystack NLP agents
Author: Florian Brand <github@florianbrand.ge>, Roland Tannous, Tuana Celik, recrudesce
License: MIT
Classifier: Programming Language :: Python :: 3
Classifier: License :: OSI Approved :: MIT License
Classifier: Operating System :: OS Independent
Project-URL: Homepage, https://github.com/rolandtannous/HaystackAgentBasicMemory
Project-URL: Bug tracker, https://github.com/rolandtannous/HaystackAgentBasicMemory/issues
Requires-Python: >=3.10
Requires-Dist: farm-haystack>=1.15.0
